nomics/__init__.py
nomics/api/__init__.py
nomics/api/api.py
nomics/api/candles.py
nomics/api/currencies.py
nomics/api/exchange_rates.py
nomics/api/markets.py
nomics/api/volume.py
tests/__init__.py
tests/test_candles.py
tests/test_currencies.py
tests/test_exchange_rates.py
tests/test_markets.py
tests/test_volume.py
tests/test_wrapper.py
nomics_python-3.1.0.dist-info/LICENSE
nomics_python-3.1.0.dist-info/METADATA
nomics_python-3.1.0.dist-info/WHEEL
nomics_python-3.1.0.dist-info/top_level.txt
nomics_python-3.1.0.dist-info/RECORD
