Metadata-Version: 2.1
Name: nomics-python
Version: 3.1.0
Summary: A python wrapper for the Nomics API
Home-page: https://github.com/TaylorFacen/nomics-python
Author: Taylor Facen
Author-email: taylor.facen@gmail.com
License: UNKNOWN
Platform: UNKNOWN
Classifier: Programming Language :: Python :: 3
Classifier: License :: OSI Approved :: MIT License
Requires-Dist: requests (>=2)
